cfn/__init__.py
cfn/__main__.py
cfn/hello/__init__.py
cfn/hello/hello.py
cjkitchehelloworld-0.0.5.dist-info/METADATA
cjkitchehelloworld-0.0.5.dist-info/RECORD
cjkitchehelloworld-0.0.5.dist-info/WHEEL
cjkitchehelloworld-0.0.5.dist-info/entry_points.txt
cjkitchehelloworld-0.0.5.dist-info/top_level.txt
