Metadata-Version: 2.1
Name: cjkitchehelloworld
Version: 0.0.5
Summary: Test package
Home-page: UNKNOWN
Author: UNKNOWN
Author-email: UNKNOWN
License: UNKNOWN
Platform: UNKNOWN
Requires-Dist: Click
